responsibleai_tabular_automl/__init__.py
responsibleai_tabular_automl/_loggerfactory.py
responsibleai_tabular_automl/automl_inference_run.py
responsibleai_tabular_automl/rai_automl.py
responsibleai_tabular_automl/version.py
responsibleai_tabular_automl-0.15.0.dist-info/METADATA
responsibleai_tabular_automl-0.15.0.dist-info/WHEEL
responsibleai_tabular_automl-0.15.0.dist-info/top_level.txt
responsibleai_tabular_automl-0.15.0.dist-info/RECORD
